setup.py
loxone_websocket_client/__init__.py
loxone_websocket_client/message.py
loxone_websocket_client/messageheader.py
loxone_websocket_client/tokenenc.py
loxone_websocket_client.egg-info/PKG-INFO
loxone_websocket_client.egg-info/SOURCES.txt
loxone_websocket_client.egg-info/dependency_links.txt
loxone_websocket_client.egg-info/requires.txt
loxone_websocket_client.egg-info/top_level.txt