Metadata-Version: 1.0
Name: loxone-websocket-client
Version: 0.3
Summary: Loxone Websocket Client Library
Home-page: https://github.com/escalate/python-loxone-ws-client
Author: Felix Börner
Author-email: github@felix-boerner.de
License: MIT
Platform: UNKNOWN
